html2text_no_md_escapes/__init__.py
html2text_no_md_escapes/cli.py
html2text_no_md_escapes/compat.py
html2text_no_md_escapes/config.py
html2text_no_md_escapes/utils.py
html2text_no_md_escapes-2020.8.9.dist-info/AUTHORS.rst
html2text_no_md_escapes-2020.8.9.dist-info/COPYING
html2text_no_md_escapes-2020.8.9.dist-info/METADATA
html2text_no_md_escapes-2020.8.9.dist-info/WHEEL
html2text_no_md_escapes-2020.8.9.dist-info/entry_points.txt
html2text_no_md_escapes-2020.8.9.dist-info/top_level.txt
html2text_no_md_escapes-2020.8.9.dist-info/RECORD
