Metadata-Version: 2.1
Name: html2text-no-md-escapes
Version: 2020.8.9
Summary: Turn HTML into equivalent Markdown-structured text.
Home-page: https://github.com/m4l1c3/html2text/
Author: Aaron Swartz
Author-email: me@aaronsw.com
Maintainer: m4l1c3
Maintainer-email: m4l1c3@protonmail.com
License: GNU GPL 3
Platform: OS Independent
Classifier: Development Status :: 5 - Production/Stable
Classifier: Intended Audience :: Developers
Classifier: License :: OSI Approved :: GNU General Public License (GPL)
Classifier: Operating System :: OS Independent
Classifier: Programming Language :: Python
Classifier: Programming Language :: Python :: 2
Classifier: Programming Language :: Python :: 2.4
Classifier: Programming Language :: Python :: 2.5
Classifier: Programming Language :: Python :: 2.6
Classifier: Programming Language :: Python :: 2.7
Classifier: Programming Language :: Python :: 3
Classifier: Programming Language :: Python :: 3.0
Classifier: Programming Language :: Python :: 3.2
Classifier: Programming Language :: Python :: 3.3
Classifier: Programming Language :: Python :: 3.4
Classifier: Programming Language :: Python :: 3.5
Classifier: Programming Language :: Python :: 3.6
